{
  "favorites": [
    {
      "coord": {
        "lon": 73.85,
        "lat": 18.52
      },
      "weather": [
        {
          "id": 500,
          "main": "Rain",
          "description": "light rain",
          "icon": "10d"
        }
      ],
      "base": "stations",
      "main": {
        "temp": 28.48,
        "pressure": 948.34,
        "humidity": 59,
        "temp_min": 28.48,
        "temp_max": 28.48,
        "sea_level": 1022.1,
        "grnd_level": 948.34
      },
      "wind": {
        "speed": 2.76,
        "deg": 154.002
      },
      "rain": {
        "3h": 0.78
      },
      "clouds": {
        "all": 64
      },
      "dt": 1521363337,
      "sys": {
        "message": 0.0131,
        "country": "IN",
        "sunrise": 1521335420,
        "sunset": 1521378906
      },
      "id": 1278710,
      "name": "Pune",
      "cod": 200
    },
    {
      "coord": {
        "lon": 77.22,
        "lat": 28.65
      },
      "weather": [
        {
          "id": 721,
          "main": "Haze",
          "description": "haze",
          "icon": "50d"
        }
      ],
      "base": "stations",
      "main": {
        "temp": 31,
        "pressure": 1013,
        "humidity": 19,
        "temp_min": 31,
        "temp_max": 31
      },
      "visibility": 5000,
      "wind": {
        "speed": 5.1,
        "deg": 300
      },
      "clouds": {
        "all": 0
      },
      "dt": 1521360000,
      "sys": {
        "type": 1,
        "id": 7809,
        "message": 0.0078,
        "country": "IN",
        "sunrise": 1521334640,
        "sunset": 1521378079
      },
      "id": 1261481,
      "name": "Delhi",
      "cod": 200
    },
    {
      "coord": {
        "lon": 77.6,
        "lat": 12.98
      },
      "weather": [
        {
          "id": 802,
          "main": "Clouds",
          "description": "scattered clouds",
          "icon": "03d"
        }
      ],
      "base": "stations",
      "main": {
        "temp": 26,
        "pressure": 1017,
        "humidity": 69,
        "temp_min": 26,
        "temp_max": 26
      },
      "visibility": 10000,
      "wind": {
        "speed": 3.6,
        "deg": 110
      },
      "clouds": {
        "all": 40
      },
      "dt": 1521351000,
      "sys": {
        "type": 1,
        "id": 7821,
        "message": 0.0505,
        "country": "IN",
        "sunrise": 1521334508,
        "sunset": 1521378017
      },
      "id": 1277333,
      "name": "Bangalore",
      "cod": 200
    },
    {
      "coord": {
        "lon": 79.83,
        "lat": 11.93
      },
      "weather": [
        {
          "id": 800,
          "main": "Clear",
          "description": "clear sky",
          "icon": "01d"
        }
      ],
      "base": "stations",
      "main": {
        "temp": 30.68,
        "pressure": 1020.4,
        "humidity": 76,
        "temp_min": 30.68,
        "temp_max": 30.68,
        "sea_level": 1023.15,
        "grnd_level": 1020.4
      },
      "wind": {
        "speed": 5.01,
        "deg": 103.502
      },
      "clouds": {
        "all": 0
      },
      "dt": 1521363780,
      "sys": {
        "message": 0.0022,
        "country": "IN",
        "sunrise": 1521333966,
        "sunset": 1521377485
      },
      "id": 3369157,
      "name": "Puducherry",
      "cod": 200
    }
  ]
}